simplematchcalc/__init__.py
simplematchcalc/calculator.py
simplematchcalc-0.1.0.dist-info/METADATA
simplematchcalc-0.1.0.dist-info/WHEEL
simplematchcalc-0.1.0.dist-info/top_level.txt
simplematchcalc-0.1.0.dist-info/RECORD
